README.md
setup.py
calendar_scheduler.egg-info/PKG-INFO
calendar_scheduler.egg-info/SOURCES.txt
calendar_scheduler.egg-info/dependency_links.txt
calendar_scheduler.egg-info/requires.txt
calendar_scheduler.egg-info/top_level.txt
scheduler/__init__.py
scheduler/enums.py
scheduler/scheduler.py
scheduler/tests/__init__.py
scheduler/tests/test_cron.py
scheduler/tests/test_date_specific.py