Metadata-Version: 2.1
Name: calendar-scheduler
Version: 0.0.2
Summary: Scheduler program
Home-page: https://github.com/parthakonda/calendar_scheduler
Author: Partha Saradhi Konda
Author-email: parthasaradhi1992@gmail.com
License: UNKNOWN
Platform: UNKNOWN
Classifier: Programming Language :: Python :: 3
Classifier: License :: OSI Approved :: MIT License
Classifier: Operating System :: OS Independent
